mlup/__init__.py
mlup/main.py
mlup-0.0.1.dist-info/LICENSE
mlup-0.0.1.dist-info/METADATA
mlup-0.0.1.dist-info/WHEEL
mlup-0.0.1.dist-info/entry_points.txt
mlup-0.0.1.dist-info/top_level.txt
mlup-0.0.1.dist-info/RECORD
